videotosmi/SMI.py
videotosmi/Video.py
videotosmi/__init__.py
videotosmi-0.0.1.dist-info/LICENSE
videotosmi-0.0.1.dist-info/METADATA
videotosmi-0.0.1.dist-info/WHEEL
videotosmi-0.0.1.dist-info/top_level.txt
videotosmi-0.0.1.dist-info/RECORD
