Metadata-Version: 2.1
Name: videotosmi
Version: 0.0.1
Summary: Create a smi file based on the video.
Home-page: https://github.com/Sotaneum/VideoToSMI
Author: Donggun LEE
Author-email: gnyotnu39@gmail.com
License: MIT
Platform: UNKNOWN
